{
	"type": "GenericCrafter",
	"name": "Exotic Liquid Melter",
	"description": "Melts rare materials into exotic liquid",
	"outputLiquid": {"liquid": "exotic-liquid", "amount": 10},
	"size": 1,
	"hasPower": true,
	"hasLiquids": true,
	"LiquidCapacity": 60.0,
	"hasItems": true,
	"itemCapacity": 50,
	"craftTime": 20,
	"updateEffect": "steam",
	"consumes": {
		"power": 5,
		"items": {
			"items": [
				{ "item": "ether", "amount": "5" }
				{ "item": "surge-alloy", "amount": "5" }
				{ "item": "thorium", "amount": "5" }
			]
		}
	},
	"requirements": [
		{ "item": "ether", "amount": 50 	},
		{ "item": "copper", "amount": 25 },
		{ "item": "graphite", "amount": 15 }
	],
	"category": "crafting",
	"research": "melter",
	"idleSound": "respawning",
	"idleSoundVolume": 0.5
}